voice_typing/__init__.py
voice_typing/main.py
voice_typing-0.1.0.dist-info/METADATA
voice_typing-0.1.0.dist-info/WHEEL
voice_typing-0.1.0.dist-info/entry_points.txt
voice_typing-0.1.0.dist-info/top_level.txt
voice_typing-0.1.0.dist-info/RECORD
