Metadata-Version: 2.1
Name: voice-typing
Version: 0.1.0
Summary: A voice typing application using tkinter and speech recognition
Home-page: https://github.com/yourusername/voice-typing
Author: Er. Harsh Raj
Author-email: your-email@example.com
Classifier: Programming Language :: Python :: 3
Classifier: License :: OSI Approved :: MIT License
Classifier: Operating System :: OS Independent
Requires-Python: >=3.6
Requires-Dist: pyautogui
Requires-Dist: SpeechRecognition
